MANIFEST.in
README.rst
setup.py
discotech/__init__.py
discotech/errors.py
discotech/utils.py
discotech.egg-info/PKG-INFO
discotech.egg-info/SOURCES.txt
discotech.egg-info/dependency_links.txt
discotech.egg-info/requires.txt
discotech.egg-info/top_level.txt
discotech/APIProviders/__init__.py
discotech/APIProviders/provider.py
discotech/APIProviders/providerSearcher.py
discotech/discoAPI/__init__.py
discotech/discoAPI/discoAPIParser.py
discotech/discoAPI/discoAPISearcher.py
discotech/discoAPI/keywordManager.py
discotech/discoAPI/parseResults.py