Metadata-Version: 1.0
Name: discotech
Version: 0.4.7
Summary: python library to help working with social media providers
Home-page: http://github.com/discoapi/discotech
Author: discoAPI Team
Author-email: groovy@discoapi.com
License: GPL
Platform: UNKNOWN
